buisciii/__init__.py
buisciii/__main__.py
buisciii/archive.py
buisciii/autoclean_sftp.py
buisciii/bioinfo_doc.py
buisciii/clean.py
buisciii/config_json.py
buisciii/copy_sftp.py
buisciii/drylab_api.py
buisciii/list.py
buisciii/new_service.py
buisciii/scratch.py
buisciii/service_json.py
buisciii/utils.py
buisciii/assets/BU_ISCIII_logo.png
buisciii/assets/css/bootstrap.min.css
buisciii/assets/outbreakinfo/get_mutations_outbreak_info.R
buisciii/assets/outbreakinfo/lablog
buisciii/assets/outbreakinfo/update_lineage_data.py
buisciii/assets/reports/md/assembly.md
buisciii/assets/reports/md/irma.md
buisciii/assets/reports/md/pikavirus.md
buisciii/assets/reports/md/plasmidid.md
buisciii/assets/reports/md/rnaseq_deg.md
buisciii/assets/reports/md/sarek.md
buisciii/assets/reports/md/taxprofiler.md
buisciii/assets/reports/md/viralrecon.md
buisciii/assets/reports/md/wgmlst_chewbbaca.md
buisciii/assets/reports/md/images/ALM-ASM.png
buisciii/assets/reports/md/images/IRMA_workflow.png
buisciii/assets/reports/md/images/KPN30_000240185_summary.png
buisciii/assets/reports/md/images/NIPH-NIPHEM.png
buisciii/assets/reports/md/images/PLOT.png
buisciii/assets/reports/md/images/SEN30_000195995_NC_013365.1.png
buisciii/assets/reports/md/images/asciigenome_screenshot.png
buisciii/assets/reports/md/images/deseq2_boxplot.png
buisciii/assets/reports/md/images/deseq2_cluster_dendogram.png
buisciii/assets/reports/md/images/deseq2_dispersion-estimate.png
buisciii/assets/reports/md/images/deseq2_heatmap-top-20-genes.png
buisciii/assets/reports/md/images/deseq2_heatmap_all.png
buisciii/assets/reports/md/images/deseq2_maplot.png
buisciii/assets/reports/md/images/deseq2_pca.png
buisciii/assets/reports/md/images/deseq2_plotSD.png
buisciii/assets/reports/md/images/deseq2_pvalue-hist.png
buisciii/assets/reports/md/images/deseq2_qc_plots.png
buisciii/assets/reports/md/images/deseq2_sample-to-sample.png
buisciii/assets/reports/md/images/dupradar_example_plot.png
buisciii_tools-2.2.13.dist-info/licenses/LICENSE
buisciii_tools-2.2.13.dist-info/METADATA
buisciii_tools-2.2.13.dist-info/WHEEL
buisciii_tools-2.2.13.dist-info/entry_points.txt
buisciii_tools-2.2.13.dist-info/top_level.txt
buisciii_tools-2.2.13.dist-info/RECORD
