Metadata-Version: 2.4
Name: buisciii-tools
Version: 2.2.13
Summary: Tools for managing and resolution of buisciii services.
Author-email: Sara Monzon <smonzon@isciii.es>, Luis Chapado <lchapado@externos.isciii.es>, Isabel Cuesta <isabel.cuesta@isciii.es>, Sarai Varona <s.varona@isciii.es>, Daniel Valle <da.valle@externos.isciii.es>, Pablo Mata <pmata@externos.isciii.es>, Victor Lopez <vmlopez@isciii.es>, Emi Arjona <eiarjona@isciii.es>, Jaime Ozaez <jaime.ozaez@isciii.es>, Juan Ledesma <juan.ledesma@isciii.es>, Sergio Olmos <sergio.olmos@externos.isciii.es>, Alejandro Bernabeu <abernabeu@isciii.es>, Alba Talavera <al
Maintainer-email: Sara Monzon <smonzon@isciii.es>, Luis Chapado <lchapado@externos.isciii.es>, Isabel Cuesta <isabel.cuesta@isciii.es>, Sarai Varona <s.varona@isciii.es>, Daniel Valle <da.valle@externos.isciii.es>, Pablo Mata <pmata@externos.isciii.es>, Victor Lopez <vmlopez@isciii.es>, Emi Arjona <eiarjona@isciii.es>, Jaime Ozaez <jaime.ozaez@isciii.es>, Juan Ledesma <juan.ledesma@isciii.es>, Sergio Olmos <sergio.olmos@externos.isciii.es>, Alejandro Bernabeu <abernabeu@isciii.es>, Alba Talavera
Project-URL: Homepage, https://github.com/BU-ISCIII/buisciii-tools
Project-URL: Issues, https://github.com/BU-ISCIII/buisciii-tools/issues
Keywords: buisciii,bioinformatics,pipeline,sequencing,NGS,next generation sequencing
License-File: LICENSE
Requires-Dist: click>=8.1.8
Requires-Dist: questionary>=2.1.0
Requires-Dist: jinja2>=3.1.5
Requires-Dist: jsonschema>=4.23.0
Requires-Dist: packaging>=24.2
Requires-Dist: prompt_toolkit>=3.0.48
Requires-Dist: rich>=13.9.4
Requires-Dist: sysrsync>=1.0.1
Requires-Dist: requests>=2.27.1
Requires-Dist: markdown>=3.3.6
Requires-Dist: pymdown-extensions>=10.4
Requires-Dist: pdfkit>=1.0.0
Requires-Dist: PyPDF2>=3.0.1
Requires-Dist: PyYAML>=6.0.2
Requires-Dist: setuptools>=68
Dynamic: license-file
